clsforyou/__init__.py
clsforyou/clsforyou.py
clsforyou/script.py
clsforyou-0.1.4.dist-info/METADATA
clsforyou-0.1.4.dist-info/WHEEL
clsforyou-0.1.4.dist-info/top_level.txt
clsforyou-0.1.4.dist-info/RECORD
