Metadata-Version: 2.1
Name: clsforyou
Version: 0.1.4
Summary: Awesome library
Home-page: https://github.com/hirokazuniimoto
Author: hirokazu
Author-email: kazumoto58427@gmail.com
License: MIT
Keywords: sample setuptools development
Platform: UNKNOWN
Classifier: Programming Language :: Python :: 3.6
Requires-Dist: requests (>=2.14.2)
